{"openapi":"3.0.3","info":{"title":"Wallet API","description":"Service for managing user balances, allowing users to retrieve, update, and manage their balance information.","version":"0.0.1"},"servers":[{"url":"http://localhost:8080"}],"paths":{"/transaction":{"post":{"tags":["transaction"],"summary":"create transaction","description":"Create a new transaction","operationId":"transaction#create","parameters":[{"name":"Source-Type","in":"header","description":"Source type header","allowEmptyValue":true,"required":true,"schema":{"type":"string","description":"Source type header","example":"game","enum":["game","server","payment"]},"example":"game"}],"requestBody":{"required":true,"content":{"application/json":{"schema":{"$ref":"#/components/schemas/CreateRequestBody"},"example":{"amount":"10.15","state":"win","transactionId":"some generated identificator"}}}},"responses":{"202":{"description":"Accepted response."},"400":{"description":"Invalid input"},"500":{"description":"Internal server error"}}}},"/transaction/health":{"get":{"tags":["transaction"],"summary":"healthcheck transaction","description":"Check if the service is running","operationId":"transaction#healthcheck","responses":{"200":{"description":"Service is healthy","content":{"application/json":{"schema":{"$ref":"#/components/schemas/HealthcheckResponseBody"},"example":{"status":"Repellat natus et."}}}}}}}},"components":{"schemas":{"CreateRequestBody":{"type":"object","properties":{"amount":{"type":"string","description":"Amount of the transaction","example":"10.15"},"state":{"type":"string","description":"State of the transaction","example":"win","enum":["win","lost"]},"transactionId":{"type":"string","description":"Transaction ID","example":"some generated identificator"}},"example":{"amount":"10.15","state":"win","transactionId":"some generated identificator"},"required":["state","amount","transactionId"]},"HealthcheckResponseBody":{"type":"object","properties":{"status":{"type":"string","description":"Service status","example":"Qui ipsa architecto."}},"example":{"status":"Rem ipsum velit aliquid quia delectus quos."},"required":["status"]}}},"tags":[{"name":"transaction","description":"The transaction service"}]}